xdisplayselect/__init__.py
xdisplayselect/__main__.py
xdisplayselect/config.py
xdisplayselect/monitor.py
xdisplayselect/monitor_config.py
xdisplayselect/user_input.py
xdisplayselect-1.0.0.dist-info/entry_points.txt
xdisplayselect-1.0.0.dist-info/LICENSE
xdisplayselect-1.0.0.dist-info/WHEEL
xdisplayselect-1.0.0.dist-info/METADATA
xdisplayselect-1.0.0.dist-info/RECORD
