Metadata-Version: 2.1
Name: xdisplayselect
Version: 1.0.0
Summary: Utility to simplify controlling monitors on linux WMs
Home-page: https://github.com/ItsDrike/xdisplayselect
License: GPL-3.0-or-later
Author: ItsDrike
Author-email: itsdrike@protonmail.com
Requires-Python: >3.9,<4
Classifier: Development Status :: 2 - Pre-Alpha
Classifier: Intended Audience :: End Users/Desktop
Classifier: License :: OSI Approved :: GNU General Public License v3 (GPLv3)
Classifier: License :: OSI Approved :: GNU General Public License v3 or later (GPLv3+)
Classifier: Natural Language :: English
Classifier: Operating System :: OS Independent
Classifier: Programming Language :: Python
Classifier: Programming Language :: Python :: 3
Classifier: Programming Language :: Python :: 3.10
Classifier: Programming Language :: Python :: 3.9
Classifier: Typing :: Typed
Requires-Dist: inquirer (>=2.10.0,<3.0.0)
Project-URL: Repository, https://github.com/ItsDrike/xdisplayselect
